{
    "culture": "zh-Hans",
    "texts": {
      "Menu:Home": "首页",
      "Welcome": "欢迎",
      "LongWelcomeMessage": "欢迎来到该应用程序. 这是一个基于ABP框架的启动项目. 有关更多信息, 请访问 abp.io.",
      "Menu:BookStore": "图书商店",
      "Menu:Books": "图书",
      "Actions": "操作",
      "Close": "关闭",
      "Delete": "删除",
      "Edit": "编辑",
      "Books": "图书管理",
      "PublishDate": "上市日期",
      "NewBook": "创建",
      "Name": "名称",
      "Type": "类型",
      "Price": "价格",
      "CreationTime": "创建时间",
      "AreYouSure": "你确定吗？",
      "AreYouSureToDelete": "你确定想要删除这一项吗？",
      "BookDeletionConfirmationMessage": "你确定要删除“{0}”这本书吗？",
      "SuccessfullyDeleted": "删除成功！",
      
      "Menu:Authors": "作者",
      "Authors": "作者管理",
      "AuthorDeletionConfirmationMessage": "你确定要删除“{0}“这个作者吗？",
      "BirthDate": "出生日期",
      "NewAuthor": "创建",
      
      "Enum:BookType:0": "Undefined",
      "Enum:BookType:1": "Adventure",
      "Enum:BookType:2": "Biography",
      "Enum:BookType:3": "Dystopia",
      "Enum:BookType:4": "Fantastic",
      "Enum:BookType:5": "Horror",
      "Enum:BookType:6": "Science",
      "Enum:BookType:7": "Science fiction",
      "Enum:BookType:8": "Poetry",

      "Permission:BookStore": "书籍商店",
      "Permission:Books": "书籍管理",
      "Permission:Books:Create": "创建书籍",
      "Permission:Books:Edit": "编辑书籍",
      "Permission:Books:Delete": "删除书籍",
      "Permission:Authors": "作者管理",
      "Permission:Authors:Create": "创建作者",
      "Permission:Authors:Edit": "编辑作者",
      "Permission:Authors:Delete": "删除作者",
      
      "BookStore:00001": "已存在相同名称的作者：{name}"
    }
  }